{
    "source_type": "ICD10PCS",
    "source_id": "GZFZZZZ",
    "status": "OK",
    "ICD10PCS_ES": [
        {
            "id": "GZFZZZZ",
            "description": "Hipnosis, para salud mental"
        }
    ],
    "UMLS_CUI": [
        {
            "id": "C0020587",
            "description": "Hypnosis"
        },
        {
            "id": "C0020587",
            "description": "Hypnosis"
        },
        {
            "id": "C0020587",
            "description": "Mental Health @ None @ Hypnosis @ None @ None @ None @ None"
        }
    ],
    "SNOMEDCT_EN": [
        {
            "id": "19997007",
            "description": "Hypnotherapy"
        },
        {
            "id": "70503004",
            "description": "Hypnotic state"
        },
        {
            "id": "151644003",
            "description": "Therapeutic hypnosis"
        },
        {
            "id": "183409005",
            "description": "Therapeutic hypnosis NOS"
        },
        {
            "id": "151646001",
            "description": "Therapeutic hypnosis NOS"
        },
        {
            "id": "151645002",
            "description": "Hypnosis for therapy"
        },
        {
            "id": "183408002",
            "description": "Hypnosis for therapy"
        }
    ],
    "SNOMEDCT_ES": [
        {
            "id": "19997007",
            "description": "hipnoterapia"
        },
        {
            "id": "70503004",
            "description": "estado hipnótico"
        }
    ],
    "wikidata_item_url": [
        "http://www.wikidata.org/entity/Q8609"
    ],
    "wikipedia_article_url": [
        {
            "afwiki": "https://af.wikipedia.org/wiki/Hipnose",
            "angwiki": "https://ang.wikipedia.org/wiki/Oferswefn",
            "arwiki": "https://ar.wikipedia.org/wiki/تنويم_مغناطيسي",
            "arzwiki": "https://arz.wikipedia.org/wiki/ايحاء",
            "astwiki": "https://ast.wikipedia.org/wiki/Hipnosis",
            "azwiki": "https://az.wikipedia.org/wiki/Hipnoz",
            "be_x_oldwiki": "https://be-tarask.wikipedia.org/wiki/Гіпноз",
            "bewiki": "https://be.wikipedia.org/wiki/Гіпноз",
            "bgwiki": "https://bg.wikipedia.org/wiki/Хипноза",
            "bnwiki": "https://bn.wikipedia.org/wiki/সম্মোহন",
            "bswiki": "https://bs.wikipedia.org/wiki/Hipnoza",
            "cawiki": "https://ca.wikipedia.org/wiki/Hipnosi",
            "ckbwiki": "https://ckb.wikipedia.org/wiki/خەواندنی_موگناتیسی",
            "cswiki": "https://cs.wikipedia.org/wiki/Hypnóza",
            "cywiki": "https://cy.wikipedia.org/wiki/Hypnosis",
            "dawiki": "https://da.wikipedia.org/wiki/Hypnose",
            "dewiki": "https://de.wikipedia.org/wiki/Hypnose",
            "dewikiquote": "https://de.wikiquote.org/wiki/Hypnose",
            "elwiki": "https://el.wikipedia.org/wiki/Ύπνωση",
            "enwiki": "https://en.wikipedia.org/wiki/Hypnosis",
            "enwikibooks": "https://en.wikibooks.org/wiki/Hypnosis",
            "enwikiquote": "https://en.wikiquote.org/wiki/Hypnotism",
            "eowiki": "https://eo.wikipedia.org/wiki/Hipnoto",
            "eswiki": "https://es.wikipedia.org/wiki/Hipnosis",
            "etwiki": "https://et.wikipedia.org/wiki/Hüpnoos",
            "etwikiquote": "https://et.wikiquote.org/wiki/Hüpnoos",
            "euwiki": "https://eu.wikipedia.org/wiki/Hipnosi",
            "fawiki": "https://fa.wikipedia.org/wiki/هیپنوتیزم",
            "fiwiki": "https://fi.wikipedia.org/wiki/Hypnoosi",
            "frwiki": "https://fr.wikipedia.org/wiki/Hypnose",
            "fywiki": "https://fy.wikipedia.org/wiki/Hypnoaze",
            "gawiki": "https://ga.wikipedia.org/wiki/Hiopnóis",
            "glwiki": "https://gl.wikipedia.org/wiki/Hipnose",
            "hewiki": "https://he.wikipedia.org/wiki/היפנוזה",
            "hiwiki": "https://hi.wikipedia.org/wiki/सम्मोहन",
            "hrwiki": "https://hr.wikipedia.org/wiki/Hipnoza",
            "huwiki": "https://hu.wikipedia.org/wiki/Hipnózis",
            "hywiki": "https://hy.wikipedia.org/wiki/Հիպնոս",
            "hywwiki": "https://hyw.wikipedia.org/wiki/Արհեստաքուն",
            "idwiki": "https://id.wikipedia.org/wiki/Hipnosis",
            "itwiki": "https://it.wikipedia.org/wiki/Ipnosi",
            "itwikiquote": "https://it.wikiquote.org/wiki/Ipnosi",
            "jawiki": "https://ja.wikipedia.org/wiki/催眠",
            "jawikibooks": "https://ja.wikibooks.org/wiki/催眠術",
            "kawiki": "https://ka.wikipedia.org/wiki/ჰიპნოზი",
            "kkwiki": "https://kk.wikipedia.org/wiki/Гипноз",
            "knwiki": "https://kn.wikipedia.org/wiki/ಸಂಮೋಹನ_ಶಾಸ್ತ್ರ",
            "kowiki": "https://ko.wikipedia.org/wiki/최면",
            "kowikibooks": "https://ko.wikibooks.org/wiki/최면",
            "kywiki": "https://ky.wikipedia.org/wiki/Гипноз",
            "lawiki": "https://la.wikipedia.org/wiki/Hypnosis",
            "ltwiki": "https://lt.wikipedia.org/wiki/Hipnozė",
            "lvwiki": "https://lv.wikipedia.org/wiki/Hipnoze",
            "mkwiki": "https://mk.wikipedia.org/wiki/Хипноза",
            "mlwiki": "https://ml.wikipedia.org/wiki/ഹിപ്നോട്ടിസം",
            "mswiki": "https://ms.wikipedia.org/wiki/Hipnosis",
            "mywiki": "https://my.wikipedia.org/wiki/စိတ်ညှို့ပညာ",
            "newiki": "https://ne.wikipedia.org/wiki/हिप्नाेसिस्",
            "nlwiki": "https://nl.wikipedia.org/wiki/Hypnose",
            "nnwiki": "https://nn.wikipedia.org/wiki/Hypnose",
            "nowiki": "https://no.wikipedia.org/wiki/Hypnose",
            "ocwiki": "https://oc.wikipedia.org/wiki/Ipnòsi",
            "plwiki": "https://pl.wikipedia.org/wiki/Hipnoza",
            "plwikiquote": "https://pl.wikiquote.org/wiki/Hipnoza",
            "ptwiki": "https://pt.wikipedia.org/wiki/Hipnose",
            "rowiki": "https://ro.wikipedia.org/wiki/Hipnoză",
            "ruwiki": "https://ru.wikipedia.org/wiki/Гипноз",
            "ruwikinews": "https://ru.wikinews.org/wiki/Категория:Гипноз",
            "sahwiki": "https://sah.wikipedia.org/wiki/Гипноз",
            "sdwiki": "https://sd.wikipedia.org/wiki/هيپناٽزم",
            "shwiki": "https://sh.wikipedia.org/wiki/Hipnoza",
            "simplewiki": "https://simple.wikipedia.org/wiki/Hypnosis",
            "siwiki": "https://si.wikipedia.org/wiki/මෝහනය",
            "skwiki": "https://sk.wikipedia.org/wiki/Hypnóza",
            "slwiki": "https://sl.wikipedia.org/wiki/Hipnoza",
            "sqwiki": "https://sq.wikipedia.org/wiki/Hipnoza",
            "srwiki": "https://sr.wikipedia.org/wiki/Хипноза",
            "svwiki": "https://sv.wikipedia.org/wiki/Hypnos",
            "tawiki": "https://ta.wikipedia.org/wiki/அறிதுயில்_நிலை",
            "tewiki": "https://te.wikipedia.org/wiki/హిప్నాటిజం",
            "thwiki": "https://th.wikipedia.org/wiki/การสะกดจิต",
            "tlwiki": "https://tl.wikipedia.org/wiki/Hipnosis",
            "trwiki": "https://tr.wikipedia.org/wiki/Hipnoz",
            "ukwiki": "https://uk.wikipedia.org/wiki/Гіпноз",
            "uzwiki": "https://uz.wikipedia.org/wiki/Gipnoz",
            "viwiki": "https://vi.wikipedia.org/wiki/Thôi_miên",
            "wuuwiki": "https://wuu.wikipedia.org/wiki/催眠",
            "yiwiki": "https://yi.wikipedia.org/wiki/היפנאזיע",
            "zh_yuewiki": "https://zh-yue.wikipedia.org/wiki/催眠",
            "zhwiki": "https://zh.wikipedia.org/wiki/催眠"
        }
    ]
}